LICENSE
README.md
pyproject.toml
setup.cfg
setup.py
docs/__init__.py
docs/changelog.py
docs/conf.py
esorm/__init__.py
esorm/aggs.py
esorm/bulk.py
esorm/error.py
esorm/esorm.py
esorm/fastapi.py
esorm/fields.py
esorm/logger.py
esorm/model.py
esorm/query.py
esorm/response.py
esorm/utils.py
esorm/watcher.py
pyesorm.egg-info/PKG-INFO
pyesorm.egg-info/SOURCES.txt
pyesorm.egg-info/dependency_links.txt
pyesorm.egg-info/requires.txt
pyesorm.egg-info/top_level.txt
tests/__init__.py
tests/conftest.py
tests/test_esorm.py