Metadata-Version: 2.1
Name: pyesorm
Version: 0.6.8
Summary: Python ElasticSearch ORM based on Pydantic
Home-page: https://github.com/wallneradam/esorm
Author: Adam Wallner
Author-email: adam.wallner@gmail.com
License: MPL-2.0
Project-URL: Bug Tracker, https://github.com/wallneradam/esorm/issues
Project-URL: Documentation, https://esorm.readthedocs.io/en/latest/
Project-URL: Source Code, https://github.com/wallneradam/esorm
Project-URL: Changelog, https://esorm.readthedocs.io/en/latest/changelog.html
Keywords: ElasticSearch,ORM,Pydantic
Classifier: Programming Language :: Python :: 3
Classifier: License :: OSI Approved :: Mozilla Public License 2.0 (MPL 2.0)
Classifier: Operating System :: OS Independent
Classifier: Intended Audience :: Developers
Classifier: Topic :: Database
Classifier: Topic :: Software Development :: Libraries :: Python Modules
Classifier: Typing :: Typed
License-File: LICENSE
Requires-Dist: typing-extensions>=4.8.0
Requires-Dist: elasticsearch<9.0.0,>=7.17.12
Requires-Dist: aiohttp<4.0.0,>=3.0.0
Requires-Dist: pydantic>=2.1.0
Provides-Extra: dev
Requires-Dist: fastapi; extra == "dev"
Requires-Dist: pytest==8.0.2; extra == "dev"
Requires-Dist: pytest-asyncio==0.21.1; extra == "dev"
Requires-Dist: pytest-spec; extra == "dev"
Requires-Dist: pytest-timeout; extra == "dev"
Requires-Dist: sphinx; extra == "dev"
Requires-Dist: sphinx-rtd-theme==1.3.0; extra == "dev"
Requires-Dist: sphinx-rtd-dark-mode==1.3.0; extra == "dev"
Requires-Dist: sphinx-autodoc-typehints; extra == "dev"
Requires-Dist: myst-parser; extra == "dev"
Requires-Dist: twine; extra == "dev"
